CHANGELOG.txt
LICENCE.txt
MANIFEST.in
README.txt
setup.py
numcek/__init__.py
numcek.egg-info/PKG-INFO
numcek.egg-info/SOURCES.txt
numcek.egg-info/dependency_links.txt
numcek.egg-info/requires.txt
numcek.egg-info/top_level.txt
numchk.egg-info/SOURCES.txt
numchk.egg-info/dependency_links.txt
numchk.egg-info/requires.txt
numchk.egg-info/top_level.txt