Metadata-Version: 2.1
Name: numcek
Version: 10.0
Summary: This is a python module for all number checks.
Home-page: UNKNOWN
Author: Subhodeep Moitra
Author-email: subhodeep2000@gmail.com
License: MIT
Keywords: numcek
Platform: UNKNOWN
Classifier: Development Status :: 5 - Production/Stable
Classifier: Intended Audience :: Education
Classifier: Operating System :: Microsoft :: Windows :: Windows 10
Classifier: License :: OSI Approved :: MIT License
Classifier: Programming Language :: Python :: 3
License-File: LICENCE.txt
